{
  "version": "v1",
  "blocklist": [],
  "data": [
    {
      "schema_version": "1.0.0",
      "id": "bonsai",
      "name": "Bonsai",
      "tagline": "A native Building Information Model authoring platform using IFC",
      "version": "0.8.1-alpha250109",
      "type": "add-on",
      "maintainer": "Dion Moult <dion@thinkmoult.com>",
      "license": [
        "SPDX:GPL-3.0-or-later"
      ],
      "blender_version_min": "4.2.0",
      "website": "https://bonsaibim.org/",
      "permissions": {
        "network": "Augin / Cove.Tool integration for VR and environmental analysis",
        "files": "Load and save IFCs, IDS, BCF, etc from disk",
        "clipboard": "Copy and paste error logs"
      },
      "tags": [
        "3D View",
        "Add Mesh",
        "Animation",
        "Camera",
        "Development",
        "Import-Export",
        "Lighting",
        "Material",
        "Modeling",
        "Mesh",
        "Node",
        "Object",
        "Pipeline",
        "Render",
        "Scene",
        "System",
        "User Interface",
        "UV"
      ],
      "platforms": [
        "linux-x64"
      ],
      "python_versions": [
        "3.11"
      ],
      "archive_url": "https://github.com/IfcOpenShell/IfcOpenShell/releases/download/bonsai-0.8.1-alpha2501090641/bonsai_py311-0.8.1-alpha250109-linux-x64.zip",
      "archive_size": 113546893,
      "archive_hash": "sha256:eba51b1550f2c961cd2d2a96fc3df119f62a7f98db4a9d02d73ea95ef28c1317"
    },
    {
      "schema_version": "1.0.0",
      "id": "bonsai",
      "name": "Bonsai",
      "tagline": "A native Building Information Model authoring platform using IFC",
      "version": "0.8.1-alpha250109",
      "type": "add-on",
      "maintainer": "Dion Moult <dion@thinkmoult.com>",
      "license": [
        "SPDX:GPL-3.0-or-later"
      ],
      "blender_version_min": "4.2.0",
      "website": "https://bonsaibim.org/",
      "permissions": {
        "network": "Augin / Cove.Tool integration for VR and environmental analysis",
        "files": "Load and save IFCs, IDS, BCF, etc from disk",
        "clipboard": "Copy and paste error logs"
      },
      "tags": [
        "3D View",
        "Add Mesh",
        "Animation",
        "Camera",
        "Development",
        "Import-Export",
        "Lighting",
        "Material",
        "Modeling",
        "Mesh",
        "Node",
        "Object",
        "Pipeline",
        "Render",
        "Scene",
        "System",
        "User Interface",
        "UV"
      ],
      "platforms": [
        "macos-arm64"
      ],
      "python_versions": [
        "3.11"
      ],
      "archive_url": "https://github.com/IfcOpenShell/IfcOpenShell/releases/download/bonsai-0.8.1-alpha2501090641/bonsai_py311-0.8.1-alpha250109-macos-arm64.zip",
      "archive_size": 106830020,
      "archive_hash": "sha256:4a1f657df06b1ed31c85c6067bd0a31369f047aa23d513019adc2470ceabb76f"
    },
    {
      "schema_version": "1.0.0",
      "id": "bonsai",
      "name": "Bonsai",
      "tagline": "A native Building Information Model authoring platform using IFC",
      "version": "0.8.1-alpha250109",
      "type": "add-on",
      "maintainer": "Dion Moult <dion@thinkmoult.com>",
      "license": [
        "SPDX:GPL-3.0-or-later"
      ],
      "blender_version_min": "4.2.0",
      "website": "https://bonsaibim.org/",
      "permissions": {
        "network": "Augin / Cove.Tool integration for VR and environmental analysis",
        "files": "Load and save IFCs, IDS, BCF, etc from disk",
        "clipboard": "Copy and paste error logs"
      },
      "tags": [
        "3D View",
        "Add Mesh",
        "Animation",
        "Camera",
        "Development",
        "Import-Export",
        "Lighting",
        "Material",
        "Modeling",
        "Mesh",
        "Node",
        "Object",
        "Pipeline",
        "Render",
        "Scene",
        "System",
        "User Interface",
        "UV"
      ],
      "platforms": [
        "macos-x64"
      ],
      "python_versions": [
        "3.11"
      ],
      "archive_url": "https://github.com/IfcOpenShell/IfcOpenShell/releases/download/bonsai-0.8.1-alpha2501090641/bonsai_py311-0.8.1-alpha250109-macos-x64.zip",
      "archive_size": 106076700,
      "archive_hash": "sha256:f67e3b18ab13692106e8a018d8b3c4a5301cb7c55791a5adadb3cb5b0c86b5b0"
    },
    {
      "schema_version": "1.0.0",
      "id": "bonsai",
      "name": "Bonsai",
      "tagline": "A native Building Information Model authoring platform using IFC",
      "version": "0.8.1-alpha250109",
      "type": "add-on",
      "maintainer": "Dion Moult <dion@thinkmoult.com>",
      "license": [
        "SPDX:GPL-3.0-or-later"
      ],
      "blender_version_min": "4.2.0",
      "website": "https://bonsaibim.org/",
      "permissions": {
        "network": "Augin / Cove.Tool integration for VR and environmental analysis",
        "files": "Load and save IFCs, IDS, BCF, etc from disk",
        "clipboard": "Copy and paste error logs"
      },
      "tags": [
        "3D View",
        "Add Mesh",
        "Animation",
        "Camera",
        "Development",
        "Import-Export",
        "Lighting",
        "Material",
        "Modeling",
        "Mesh",
        "Node",
        "Object",
        "Pipeline",
        "Render",
        "Scene",
        "System",
        "User Interface",
        "UV"
      ],
      "platforms": [
        "windows-x64"
      ],
      "python_versions": [
        "3.11"
      ],
      "archive_url": "https://github.com/IfcOpenShell/IfcOpenShell/releases/download/bonsai-0.8.1-alpha2501090641/bonsai_py311-0.8.1-alpha250109-windows-x64.zip",
      "archive_size": 84570774,
      "archive_hash": "sha256:9217b84ca381d5a9a0a8fa9250acf19e9101c1b0637765d488ef5bfb65809bfb"
    }
  ]
}
