{
  "version": "v1",
  "blocklist": [],
  "data": [
    {
      "schema_version": "1.0.0",
      "id": "bonsai",
      "name": "Bonsai",
      "tagline": "A native Building Information Model authoring platform using IFC",
      "version": "0.8.1-alpha250207",
      "type": "add-on",
      "maintainer": "Dion Moult <dion@thinkmoult.com>",
      "license": [
        "SPDX:GPL-3.0-or-later"
      ],
      "blender_version_min": "4.2.0",
      "website": "https://bonsaibim.org/",
      "permissions": {
        "network": "Augin / Cove.Tool integration for VR and environmental analysis",
        "files": "Load and save IFCs, IDS, BCF, etc from disk",
        "clipboard": "Copy and paste error logs"
      },
      "tags": [
        "3D View",
        "Add Mesh",
        "Animation",
        "Camera",
        "Development",
        "Import-Export",
        "Lighting",
        "Material",
        "Modeling",
        "Mesh",
        "Node",
        "Object",
        "Pipeline",
        "Render",
        "Scene",
        "System",
        "User Interface",
        "UV"
      ],
      "platforms": [
        "linux-x64"
      ],
      "python_versions": [
        "3.11"
      ],
      "archive_url": "https://github.com/IfcOpenShell/IfcOpenShell/releases/download/bonsai-0.8.1-alpha2502071253/bonsai_py311-0.8.1-alpha250207-linux-x64.zip",
      "archive_size": 113555886,
      "archive_hash": "sha256:25a858071c62278817b5abf678ad61a1199bc7d5e10ab3946a0470ae1db7b7db"
    },
    {
      "schema_version": "1.0.0",
      "id": "bonsai",
      "name": "Bonsai",
      "tagline": "A native Building Information Model authoring platform using IFC",
      "version": "0.8.1-alpha250207",
      "type": "add-on",
      "maintainer": "Dion Moult <dion@thinkmoult.com>",
      "license": [
        "SPDX:GPL-3.0-or-later"
      ],
      "blender_version_min": "4.2.0",
      "website": "https://bonsaibim.org/",
      "permissions": {
        "network": "Augin / Cove.Tool integration for VR and environmental analysis",
        "files": "Load and save IFCs, IDS, BCF, etc from disk",
        "clipboard": "Copy and paste error logs"
      },
      "tags": [
        "3D View",
        "Add Mesh",
        "Animation",
        "Camera",
        "Development",
        "Import-Export",
        "Lighting",
        "Material",
        "Modeling",
        "Mesh",
        "Node",
        "Object",
        "Pipeline",
        "Render",
        "Scene",
        "System",
        "User Interface",
        "UV"
      ],
      "platforms": [
        "macos-arm64"
      ],
      "python_versions": [
        "3.11"
      ],
      "archive_url": "https://github.com/IfcOpenShell/IfcOpenShell/releases/download/bonsai-0.8.1-alpha2502071253/bonsai_py311-0.8.1-alpha250207-macos-arm64.zip",
      "archive_size": 107213833,
      "archive_hash": "sha256:9a8fdd5c31d3068a2a5a452aed0a8cc5ec22519eb52c7931eb2566980463c63d"
    },
    {
      "schema_version": "1.0.0",
      "id": "bonsai",
      "name": "Bonsai",
      "tagline": "A native Building Information Model authoring platform using IFC",
      "version": "0.8.1-alpha250207",
      "type": "add-on",
      "maintainer": "Dion Moult <dion@thinkmoult.com>",
      "license": [
        "SPDX:GPL-3.0-or-later"
      ],
      "blender_version_min": "4.2.0",
      "website": "https://bonsaibim.org/",
      "permissions": {
        "network": "Augin / Cove.Tool integration for VR and environmental analysis",
        "files": "Load and save IFCs, IDS, BCF, etc from disk",
        "clipboard": "Copy and paste error logs"
      },
      "tags": [
        "3D View",
        "Add Mesh",
        "Animation",
        "Camera",
        "Development",
        "Import-Export",
        "Lighting",
        "Material",
        "Modeling",
        "Mesh",
        "Node",
        "Object",
        "Pipeline",
        "Render",
        "Scene",
        "System",
        "User Interface",
        "UV"
      ],
      "platforms": [
        "macos-x64"
      ],
      "python_versions": [
        "3.11"
      ],
      "archive_url": "https://github.com/IfcOpenShell/IfcOpenShell/releases/download/bonsai-0.8.1-alpha2502071253/bonsai_py311-0.8.1-alpha250207-macos-x64.zip",
      "archive_size": 105547266,
      "archive_hash": "sha256:88e555f445478885f1ce8e265be37bfa97d0512aa8e964f53ab85d293e6e26d2"
    },
    {
      "schema_version": "1.0.0",
      "id": "bonsai",
      "name": "Bonsai",
      "tagline": "A native Building Information Model authoring platform using IFC",
      "version": "0.8.1-alpha250207",
      "type": "add-on",
      "maintainer": "Dion Moult <dion@thinkmoult.com>",
      "license": [
        "SPDX:GPL-3.0-or-later"
      ],
      "blender_version_min": "4.2.0",
      "website": "https://bonsaibim.org/",
      "permissions": {
        "network": "Augin / Cove.Tool integration for VR and environmental analysis",
        "files": "Load and save IFCs, IDS, BCF, etc from disk",
        "clipboard": "Copy and paste error logs"
      },
      "tags": [
        "3D View",
        "Add Mesh",
        "Animation",
        "Camera",
        "Development",
        "Import-Export",
        "Lighting",
        "Material",
        "Modeling",
        "Mesh",
        "Node",
        "Object",
        "Pipeline",
        "Render",
        "Scene",
        "System",
        "User Interface",
        "UV"
      ],
      "platforms": [
        "windows-x64"
      ],
      "python_versions": [
        "3.11"
      ],
      "archive_url": "https://github.com/IfcOpenShell/IfcOpenShell/releases/download/bonsai-0.8.1-alpha2502071253/bonsai_py311-0.8.1-alpha250207-windows-x64.zip",
      "archive_size": 91778978,
      "archive_hash": "sha256:7abf2a5d9374998d27e9738572aeba938d19020b9d4a15fdabf134b02e98d371"
    }
  ]
}
