{
  "version": "v1",
  "blocklist": [],
  "data": [
    {
      "schema_version": "1.0.0",
      "id": "bonsai",
      "name": "Bonsai",
      "tagline": "A native Building Information Model authoring platform using IFC",
      "version": "0.8.1-alpha250115",
      "type": "add-on",
      "maintainer": "Dion Moult <dion@thinkmoult.com>",
      "license": [
        "SPDX:GPL-3.0-or-later"
      ],
      "blender_version_min": "4.2.0",
      "website": "https://bonsaibim.org/",
      "permissions": {
        "network": "Augin / Cove.Tool integration for VR and environmental analysis",
        "files": "Load and save IFCs, IDS, BCF, etc from disk",
        "clipboard": "Copy and paste error logs"
      },
      "tags": [
        "3D View",
        "Add Mesh",
        "Animation",
        "Camera",
        "Development",
        "Import-Export",
        "Lighting",
        "Material",
        "Modeling",
        "Mesh",
        "Node",
        "Object",
        "Pipeline",
        "Render",
        "Scene",
        "System",
        "User Interface",
        "UV"
      ],
      "platforms": [
        "linux-x64"
      ],
      "python_versions": [
        "3.11"
      ],
      "archive_url": "https://github.com/IfcOpenShell/IfcOpenShell/releases/download/bonsai-0.8.1-alpha2501150847/bonsai_py311-0.8.1-alpha250115-linux-x64.zip",
      "archive_size": 113585084,
      "archive_hash": "sha256:f1d12be987c5c577ab7abe308be23cf5a03aa8bdbd56a77792fe4bcc29296537"
    },
    {
      "schema_version": "1.0.0",
      "id": "bonsai",
      "name": "Bonsai",
      "tagline": "A native Building Information Model authoring platform using IFC",
      "version": "0.8.1-alpha250115",
      "type": "add-on",
      "maintainer": "Dion Moult <dion@thinkmoult.com>",
      "license": [
        "SPDX:GPL-3.0-or-later"
      ],
      "blender_version_min": "4.2.0",
      "website": "https://bonsaibim.org/",
      "permissions": {
        "network": "Augin / Cove.Tool integration for VR and environmental analysis",
        "files": "Load and save IFCs, IDS, BCF, etc from disk",
        "clipboard": "Copy and paste error logs"
      },
      "tags": [
        "3D View",
        "Add Mesh",
        "Animation",
        "Camera",
        "Development",
        "Import-Export",
        "Lighting",
        "Material",
        "Modeling",
        "Mesh",
        "Node",
        "Object",
        "Pipeline",
        "Render",
        "Scene",
        "System",
        "User Interface",
        "UV"
      ],
      "platforms": [
        "macos-arm64"
      ],
      "python_versions": [
        "3.11"
      ],
      "archive_url": "https://github.com/IfcOpenShell/IfcOpenShell/releases/download/bonsai-0.8.1-alpha2501150847/bonsai_py311-0.8.1-alpha250115-macos-arm64.zip",
      "archive_size": 106868618,
      "archive_hash": "sha256:b6aa09b4170f941a8d6f011d2c3886fa157c4a63c910d7ff5bdf0fae8aa7be05"
    },
    {
      "schema_version": "1.0.0",
      "id": "bonsai",
      "name": "Bonsai",
      "tagline": "A native Building Information Model authoring platform using IFC",
      "version": "0.8.1-alpha250115",
      "type": "add-on",
      "maintainer": "Dion Moult <dion@thinkmoult.com>",
      "license": [
        "SPDX:GPL-3.0-or-later"
      ],
      "blender_version_min": "4.2.0",
      "website": "https://bonsaibim.org/",
      "permissions": {
        "network": "Augin / Cove.Tool integration for VR and environmental analysis",
        "files": "Load and save IFCs, IDS, BCF, etc from disk",
        "clipboard": "Copy and paste error logs"
      },
      "tags": [
        "3D View",
        "Add Mesh",
        "Animation",
        "Camera",
        "Development",
        "Import-Export",
        "Lighting",
        "Material",
        "Modeling",
        "Mesh",
        "Node",
        "Object",
        "Pipeline",
        "Render",
        "Scene",
        "System",
        "User Interface",
        "UV"
      ],
      "platforms": [
        "macos-x64"
      ],
      "python_versions": [
        "3.11"
      ],
      "archive_url": "https://github.com/IfcOpenShell/IfcOpenShell/releases/download/bonsai-0.8.1-alpha2501150847/bonsai_py311-0.8.1-alpha250115-macos-x64.zip",
      "archive_size": 106114616,
      "archive_hash": "sha256:3c719fee765fd3ae7412d2b91522517408af796acf90881fb5183197a91665fd"
    },
    {
      "schema_version": "1.0.0",
      "id": "bonsai",
      "name": "Bonsai",
      "tagline": "A native Building Information Model authoring platform using IFC",
      "version": "0.8.1-alpha250115",
      "type": "add-on",
      "maintainer": "Dion Moult <dion@thinkmoult.com>",
      "license": [
        "SPDX:GPL-3.0-or-later"
      ],
      "blender_version_min": "4.2.0",
      "website": "https://bonsaibim.org/",
      "permissions": {
        "network": "Augin / Cove.Tool integration for VR and environmental analysis",
        "files": "Load and save IFCs, IDS, BCF, etc from disk",
        "clipboard": "Copy and paste error logs"
      },
      "tags": [
        "3D View",
        "Add Mesh",
        "Animation",
        "Camera",
        "Development",
        "Import-Export",
        "Lighting",
        "Material",
        "Modeling",
        "Mesh",
        "Node",
        "Object",
        "Pipeline",
        "Render",
        "Scene",
        "System",
        "User Interface",
        "UV"
      ],
      "platforms": [
        "windows-x64"
      ],
      "python_versions": [
        "3.11"
      ],
      "archive_url": "https://github.com/IfcOpenShell/IfcOpenShell/releases/download/bonsai-0.8.1-alpha2501150847/bonsai_py311-0.8.1-alpha250115-windows-x64.zip",
      "archive_size": 84608342,
      "archive_hash": "sha256:88897472319e6befd9bbb48cd4f520da98382ca84603fdbea51b04f7703d0def"
    }
  ]
}
