{
  "version": "v1",
  "blocklist": [],
  "data": [
    {
      "schema_version": "1.0.0",
      "id": "bonsai",
      "name": "Bonsai",
      "tagline": "A native Building Information Model authoring platform using IFC",
      "version": "0.8.1-alpha241223",
      "type": "add-on",
      "maintainer": "Dion Moult <dion@thinkmoult.com>",
      "license": [
        "SPDX:GPL-3.0-or-later"
      ],
      "blender_version_min": "4.2.0",
      "website": "https://bonsaibim.org/",
      "permissions": {
        "network": "Augin / Cove.Tool integration for VR and environmental analysis",
        "files": "Load and save IFCs, IDS, BCF, etc from disk",
        "clipboard": "Copy and paste error logs"
      },
      "tags": [
        "3D View",
        "Add Mesh",
        "Animation",
        "Camera",
        "Development",
        "Import-Export",
        "Lighting",
        "Material",
        "Modeling",
        "Mesh",
        "Node",
        "Object",
        "Pipeline",
        "Render",
        "Scene",
        "System",
        "User Interface",
        "UV"
      ],
      "platforms": [
        "linux-x64"
      ],
      "python_versions": [
        "3.11"
      ],
      "archive_url": "https://github.com/IfcOpenShell/IfcOpenShell/releases/download/bonsai-0.8.1-alpha2412231033/bonsai_py311-0.8.1-alpha241223-linux-x64.zip",
      "archive_size": 113417680,
      "archive_hash": "sha256:a6b579757e60f50f596f48ce0e95c8c1d662f954356e6e73d9e1d7a0bd422abf"
    },
    {
      "schema_version": "1.0.0",
      "id": "bonsai",
      "name": "Bonsai",
      "tagline": "A native Building Information Model authoring platform using IFC",
      "version": "0.8.1-alpha241223",
      "type": "add-on",
      "maintainer": "Dion Moult <dion@thinkmoult.com>",
      "license": [
        "SPDX:GPL-3.0-or-later"
      ],
      "blender_version_min": "4.2.0",
      "website": "https://bonsaibim.org/",
      "permissions": {
        "network": "Augin / Cove.Tool integration for VR and environmental analysis",
        "files": "Load and save IFCs, IDS, BCF, etc from disk",
        "clipboard": "Copy and paste error logs"
      },
      "tags": [
        "3D View",
        "Add Mesh",
        "Animation",
        "Camera",
        "Development",
        "Import-Export",
        "Lighting",
        "Material",
        "Modeling",
        "Mesh",
        "Node",
        "Object",
        "Pipeline",
        "Render",
        "Scene",
        "System",
        "User Interface",
        "UV"
      ],
      "platforms": [
        "macos-arm64"
      ],
      "python_versions": [
        "3.11"
      ],
      "archive_url": "https://github.com/IfcOpenShell/IfcOpenShell/releases/download/bonsai-0.8.1-alpha2412231033/bonsai_py311-0.8.1-alpha241223-macos-arm64.zip",
      "archive_size": 106614932,
      "archive_hash": "sha256:f2069705b4cc928d5233517522ae0a217f155eb6d8219608fbdc5263832e9f50"
    },
    {
      "schema_version": "1.0.0",
      "id": "bonsai",
      "name": "Bonsai",
      "tagline": "A native Building Information Model authoring platform using IFC",
      "version": "0.8.1-alpha241223",
      "type": "add-on",
      "maintainer": "Dion Moult <dion@thinkmoult.com>",
      "license": [
        "SPDX:GPL-3.0-or-later"
      ],
      "blender_version_min": "4.2.0",
      "website": "https://bonsaibim.org/",
      "permissions": {
        "network": "Augin / Cove.Tool integration for VR and environmental analysis",
        "files": "Load and save IFCs, IDS, BCF, etc from disk",
        "clipboard": "Copy and paste error logs"
      },
      "tags": [
        "3D View",
        "Add Mesh",
        "Animation",
        "Camera",
        "Development",
        "Import-Export",
        "Lighting",
        "Material",
        "Modeling",
        "Mesh",
        "Node",
        "Object",
        "Pipeline",
        "Render",
        "Scene",
        "System",
        "User Interface",
        "UV"
      ],
      "platforms": [
        "macos-x64"
      ],
      "python_versions": [
        "3.11"
      ],
      "archive_url": "https://github.com/IfcOpenShell/IfcOpenShell/releases/download/bonsai-0.8.1-alpha2412231033/bonsai_py311-0.8.1-alpha241223-macos-x64.zip",
      "archive_size": 105913700,
      "archive_hash": "sha256:61f40cbc16c4f88eaca8f270d415d99be4ae87d1c2ea91a599ddbb0886a8e476"
    },
    {
      "schema_version": "1.0.0",
      "id": "bonsai",
      "name": "Bonsai",
      "tagline": "A native Building Information Model authoring platform using IFC",
      "version": "0.8.1-alpha241223",
      "type": "add-on",
      "maintainer": "Dion Moult <dion@thinkmoult.com>",
      "license": [
        "SPDX:GPL-3.0-or-later"
      ],
      "blender_version_min": "4.2.0",
      "website": "https://bonsaibim.org/",
      "permissions": {
        "network": "Augin / Cove.Tool integration for VR and environmental analysis",
        "files": "Load and save IFCs, IDS, BCF, etc from disk",
        "clipboard": "Copy and paste error logs"
      },
      "tags": [
        "3D View",
        "Add Mesh",
        "Animation",
        "Camera",
        "Development",
        "Import-Export",
        "Lighting",
        "Material",
        "Modeling",
        "Mesh",
        "Node",
        "Object",
        "Pipeline",
        "Render",
        "Scene",
        "System",
        "User Interface",
        "UV"
      ],
      "platforms": [
        "windows-x64"
      ],
      "python_versions": [
        "3.11"
      ],
      "archive_url": "https://github.com/IfcOpenShell/IfcOpenShell/releases/download/bonsai-0.8.1-alpha2412231033/bonsai_py311-0.8.1-alpha241223-windows-x64.zip",
      "archive_size": 84494983,
      "archive_hash": "sha256:3d996175d2cf47bc04758455979e30409bfb9deeae81969b8b889bcdfa6a9f87"
    }
  ]
}
