{
  "version": "v1",
  "blocklist": [],
  "data": [
    {
      "schema_version": "1.0.0",
      "id": "bonsai",
      "name": "Bonsai",
      "tagline": "A native Building Information Model authoring platform using IFC",
      "version": "0.8.4-alpha250727",
      "type": "add-on",
      "maintainer": "Dion Moult <dion@thinkmoult.com>",
      "license": [
        "SPDX:GPL-3.0-or-later"
      ],
      "blender_version_min": "4.2.0",
      "website": "https://bonsaibim.org/",
      "permissions": {
        "network": "Augin / Cove.Tool integration for VR and environmental analysis",
        "files": "Load and save IFCs, IDS, BCF, etc from disk",
        "clipboard": "Copy and paste error logs"
      },
      "tags": [
        "3D View",
        "Add Mesh",
        "Animation",
        "Camera",
        "Development",
        "Import-Export",
        "Lighting",
        "Material",
        "Modeling",
        "Mesh",
        "Node",
        "Object",
        "Pipeline",
        "Render",
        "Scene",
        "System",
        "User Interface",
        "UV"
      ],
      "platforms": [
        "linux-x64"
      ],
      "python_versions": [
        "3.11"
      ],
      "archive_url": "https://github.com/IfcOpenShell/IfcOpenShell/releases/download/bonsai-0.8.4-alpha2507271454/bonsai_py311-0.8.4-alpha250727-linux-x64.zip",
      "archive_size": 119554826,
      "archive_hash": "sha256:3aa2b2e5d2c469f347baf2cbf4f12c66ddcb6f3e5ed61a45532c48a163a185a2"
    },
    {
      "schema_version": "1.0.0",
      "id": "bonsai",
      "name": "Bonsai",
      "tagline": "A native Building Information Model authoring platform using IFC",
      "version": "0.8.4-alpha250727",
      "type": "add-on",
      "maintainer": "Dion Moult <dion@thinkmoult.com>",
      "license": [
        "SPDX:GPL-3.0-or-later"
      ],
      "blender_version_min": "4.2.0",
      "website": "https://bonsaibim.org/",
      "permissions": {
        "network": "Augin / Cove.Tool integration for VR and environmental analysis",
        "files": "Load and save IFCs, IDS, BCF, etc from disk",
        "clipboard": "Copy and paste error logs"
      },
      "tags": [
        "3D View",
        "Add Mesh",
        "Animation",
        "Camera",
        "Development",
        "Import-Export",
        "Lighting",
        "Material",
        "Modeling",
        "Mesh",
        "Node",
        "Object",
        "Pipeline",
        "Render",
        "Scene",
        "System",
        "User Interface",
        "UV"
      ],
      "platforms": [
        "macos-arm64"
      ],
      "python_versions": [
        "3.11"
      ],
      "archive_url": "https://github.com/IfcOpenShell/IfcOpenShell/releases/download/bonsai-0.8.4-alpha2507271454/bonsai_py311-0.8.4-alpha250727-macos-arm64.zip",
      "archive_size": 112549106,
      "archive_hash": "sha256:787493f2a8e69bda3597c5ae05b1dd2f35817e681217680dc267718e7ae3d557"
    },
    {
      "schema_version": "1.0.0",
      "id": "bonsai",
      "name": "Bonsai",
      "tagline": "A native Building Information Model authoring platform using IFC",
      "version": "0.8.4-alpha250727",
      "type": "add-on",
      "maintainer": "Dion Moult <dion@thinkmoult.com>",
      "license": [
        "SPDX:GPL-3.0-or-later"
      ],
      "blender_version_min": "4.2.0",
      "website": "https://bonsaibim.org/",
      "permissions": {
        "network": "Augin / Cove.Tool integration for VR and environmental analysis",
        "files": "Load and save IFCs, IDS, BCF, etc from disk",
        "clipboard": "Copy and paste error logs"
      },
      "tags": [
        "3D View",
        "Add Mesh",
        "Animation",
        "Camera",
        "Development",
        "Import-Export",
        "Lighting",
        "Material",
        "Modeling",
        "Mesh",
        "Node",
        "Object",
        "Pipeline",
        "Render",
        "Scene",
        "System",
        "User Interface",
        "UV"
      ],
      "platforms": [
        "macos-x64"
      ],
      "python_versions": [
        "3.11"
      ],
      "archive_url": "https://github.com/IfcOpenShell/IfcOpenShell/releases/download/bonsai-0.8.4-alpha2507271454/bonsai_py311-0.8.4-alpha250727-macos-x64.zip",
      "archive_size": 109581028,
      "archive_hash": "sha256:e268ac3cd8b60a03f669d8eaf9050ca31dc5d4556af809df42771dc5a8181b2e"
    },
    {
      "schema_version": "1.0.0",
      "id": "bonsai",
      "name": "Bonsai",
      "tagline": "A native Building Information Model authoring platform using IFC",
      "version": "0.8.4-alpha250727",
      "type": "add-on",
      "maintainer": "Dion Moult <dion@thinkmoult.com>",
      "license": [
        "SPDX:GPL-3.0-or-later"
      ],
      "blender_version_min": "4.2.0",
      "website": "https://bonsaibim.org/",
      "permissions": {
        "network": "Augin / Cove.Tool integration for VR and environmental analysis",
        "files": "Load and save IFCs, IDS, BCF, etc from disk",
        "clipboard": "Copy and paste error logs"
      },
      "tags": [
        "3D View",
        "Add Mesh",
        "Animation",
        "Camera",
        "Development",
        "Import-Export",
        "Lighting",
        "Material",
        "Modeling",
        "Mesh",
        "Node",
        "Object",
        "Pipeline",
        "Render",
        "Scene",
        "System",
        "User Interface",
        "UV"
      ],
      "platforms": [
        "windows-x64"
      ],
      "python_versions": [
        "3.11"
      ],
      "archive_url": "https://github.com/IfcOpenShell/IfcOpenShell/releases/download/bonsai-0.8.4-alpha2507271454/bonsai_py311-0.8.4-alpha250727-windows-x64.zip",
      "archive_size": 93313695,
      "archive_hash": "sha256:329092cc6328e162084a178931ad41307b30eb7d0ef8b601aa5b2d3fed6f3c46"
    }
  ]
}
